<annotation verified="yes">
    <folder>Annotation</folder>
    <filename>20201003_172349_131.MP4#t=152.jpg</filename>
    <path>video-labeling-PascalVOC-export/Annotations/20201003_172349_131.MP4#t=152.jpg</path>
    <source>
        <database>Unknown</database>
    </source>
    <size>
        <width>1920</width>
        <height>1080</height>
        <depth>3</depth>
    </size>
    <segmented>0</segmented>
    <object>
    <name>ttcs_right_lane_closed_ahead</name>
    <pose>Unspecified</pose>
    <truncated>0</truncated>
    <difficult>0</difficult>
    <bndbox>
        <xmin>1308.507795100223</xmin>
        <ymin>488.8069306930693</ymin>
        <xmax>1481.692650334076</xmax>
        <ymax>812.8069306930693</ymax>
    </bndbox>
</object><object>
    <name>ttcs_right_lane_reduction</name>
    <pose>Unspecified</pose>
    <truncated>0</truncated>
    <difficult>0</difficult>
    <bndbox>
        <xmin>936.4810690423163</xmin>
        <ymin>631.0247524752475</ymin>
        <xmax>997.4164810690424</xmax>
        <ymax>747.5792079207921</ymax>
    </bndbox>
</object>
</annotation>
