<annotation verified="yes">
    <folder>Annotation</folder>
    <filename>roadmark_1400.jpg</filename>
    <path>RoadMarking-Labelling-PascalVOC-export/Annotations/roadmark_1400.jpg</path>
    <source>
        <database>Unknown</database>
    </source>
    <size>
        <width>800</width>
        <height>600</height>
        <depth>3</depth>
    </size>
    <segmented>0</segmented>
    <object>
    <name>speed_35</name>
    <pose>Unspecified</pose>
    <truncated>0</truncated>
    <difficult>0</difficult>
    <bndbox>
        <xmin>59.4847775175644</xmin>
        <ymin>348.4399375975039</ymin>
        <xmax>222.4824355971897</xmax>
        <ymax>398.0499219968799</ymax>
    </bndbox>
</object><object>
    <name>speed_35</name>
    <pose>Unspecified</pose>
    <truncated>0</truncated>
    <difficult>0</difficult>
    <bndbox>
        <xmin>289.92974238875877</xmin>
        <ymin>346.09984399375975</ymin>
        <xmax>421.54566744730676</xmax>
        <ymax>401.32605304212166</ymax>
    </bndbox>
</object>
</annotation>
