<annotation verified="yes">
    <folder>Annotation</folder>
    <filename>roadmark_0516.jpg</filename>
    <path>RoadMarking-Labelling-PascalVOC-export/Annotations/roadmark_0516.jpg</path>
    <source>
        <database>Unknown</database>
    </source>
    <size>
        <width>800</width>
        <height>600</height>
        <depth>3</depth>
    </size>
    <segmented>0</segmented>
    <object>
    <name>left_turn</name>
    <pose>Unspecified</pose>
    <truncated>0</truncated>
    <difficult>0</difficult>
    <bndbox>
        <xmin>119.90632318501171</xmin>
        <ymin>343.29173166926677</ymin>
        <xmax>173.7704918032787</xmax>
        <ymax>362.94851794071764</ymax>
    </bndbox>
</object>
</annotation>
