<annotation verified="yes">
    <folder>Annotation</folder>
    <filename>roadmark_0788.jpg</filename>
    <path>RoadMarking-Labelling-PascalVOC-export/Annotations/roadmark_0788.jpg</path>
    <source>
        <database>Unknown</database>
    </source>
    <size>
        <width>800</width>
        <height>600</height>
        <depth>3</depth>
    </size>
    <segmented>0</segmented>
    <object>
    <name>left_turn</name>
    <pose>Unspecified</pose>
    <truncated>0</truncated>
    <difficult>0</difficult>
    <bndbox>
        <xmin>60.42154566744731</xmin>
        <ymin>322.2308892355694</ymin>
        <xmax>117.56440281030446</xmax>
        <ymax>339.5475819032761</ymax>
    </bndbox>
</object>
</annotation>
