<annotation verified="yes">
    <folder>Annotation</folder>
    <filename>roadmark_0208.jpg</filename>
    <path>RoadMarking-Labelling-PascalVOC-export/Annotations/roadmark_0208.jpg</path>
    <source>
        <database>Unknown</database>
    </source>
    <size>
        <width>800</width>
        <height>600</height>
        <depth>3</depth>
    </size>
    <segmented>0</segmented>
    <object>
    <name>speed_40</name>
    <pose>Unspecified</pose>
    <truncated>0</truncated>
    <difficult>0</difficult>
    <bndbox>
        <xmin>162.52927400468386</xmin>
        <ymin>336.73946957878314</ymin>
        <xmax>276.3466042154567</xmax>
        <ymax>373.71294851794073</ymax>
    </bndbox>
</object><object>
    <name>speed_40</name>
    <pose>Unspecified</pose>
    <truncated>0</truncated>
    <difficult>0</difficult>
    <bndbox>
        <xmin>339.5784543325527</xmin>
        <ymin>336.73946957878314</ymin>
        <xmax>437.00234192037476</xmax>
        <ymax>374.6489859594384</ymax>
    </bndbox>
</object>
</annotation>
