<annotation verified="yes">
    <folder>Annotation</folder>
    <filename>roadmark_0432.jpg</filename>
    <path>RoadMarking-Labelling-PascalVOC-export/Annotations/roadmark_0432.jpg</path>
    <source>
        <database>Unknown</database>
    </source>
    <size>
        <width>800</width>
        <height>600</height>
        <depth>3</depth>
    </size>
    <segmented>0</segmented>
    <object>
    <name>stop</name>
    <pose>Unspecified</pose>
    <truncated>0</truncated>
    <difficult>0</difficult>
    <bndbox>
        <xmin>350.81967213114757</xmin>
        <ymin>320.8268330733229</ymin>
        <xmax>427.63466042154573</xmax>
        <ymax>337.207488299532</ymax>
    </bndbox>
</object>
</annotation>
