<annotation verified="yes">
    <folder>Annotation</folder>
    <filename>roadmark_1097.jpg</filename>
    <path>RoadMarking-Labelling-PascalVOC-export/Annotations/roadmark_1097.jpg</path>
    <source>
        <database>Unknown</database>
    </source>
    <size>
        <width>800</width>
        <height>600</height>
        <depth>3</depth>
    </size>
    <segmented>0</segmented>
    <object>
    <name>right_straight</name>
    <pose>Unspecified</pose>
    <truncated>0</truncated>
    <difficult>0</difficult>
    <bndbox>
        <xmin>365.807962529274</xmin>
        <ymin>334.8673946957878</ymin>
        <xmax>457.6112412177986</xmax>
        <ymax>362.4804992199688</ymax>
    </bndbox>
</object>
</annotation>
