<annotation verified="yes">
    <folder>Annotation</folder>
    <filename>roadmark_0114.jpg</filename>
    <path>RoadMarking-Labelling-PascalVOC-export/Annotations/roadmark_0114.jpg</path>
    <source>
        <database>Unknown</database>
    </source>
    <size>
        <width>800</width>
        <height>600</height>
        <depth>3</depth>
    </size>
    <segmented>0</segmented>
    <object>
    <name>left_turn</name>
    <pose>Unspecified</pose>
    <truncated>0</truncated>
    <difficult>0</difficult>
    <bndbox>
        <xmin>253.864168618267</xmin>
        <ymin>306.3182527301092</ymin>
        <xmax>323.1850117096019</xmax>
        <ymax>354.05616224648986</ymax>
    </bndbox>
</object><object>
    <name>left_turn</name>
    <pose>Unspecified</pose>
    <truncated>0</truncated>
    <difficult>0</difficult>
    <bndbox>
        <xmin>388.29039812646374</xmin>
        <ymin>308.65834633385333</ymin>
        <xmax>476.34660421545675</xmax>
        <ymax>355.4602184087363</ymax>
    </bndbox>
</object>
</annotation>
